{"is_source_file": false, "format": "", "description": "", "external_files": [], "external_methods": [], "published": [], "classes": [], "methods": [], "calls": [], "search-terms": [], "state": 2, "file_id": 10, "knowledge_revision": 29, "git_revision": "4fe5d8ef9fdfb148337cb5ef3a7c20beb770376d", "hash": "d34318d3029da96977a1475d7e90bb4f", "format-version": 4, "code-base-name": "voice_recorder_frontend", "filename": "voice_recorder_frontend/src/index.css", "revision_history": [{"29": "4fe5d8ef9fdfb148337cb5ef3a7c20beb770376d"}]}